rest_social_email_auth/__init__.py
rest_social_email_auth/admin.py
rest_social_email_auth/app_settings.py
rest_social_email_auth/apps.py
rest_social_email_auth/authentication.py
rest_social_email_auth/factories.py
rest_social_email_auth/generics.py
rest_social_email_auth/managers.py
rest_social_email_auth/models.py
rest_social_email_auth/serializers.py
rest_social_email_auth/signals.py
rest_social_email_auth/urls.py
rest_social_email_auth/utils.py
rest_social_email_auth/views.py
rest_social_email_auth/__pycache__/__init__.cpython-36.pyc
rest_social_email_auth/__pycache__/admin.cpython-36.pyc
rest_social_email_auth/__pycache__/app_settings.cpython-36.pyc
rest_social_email_auth/__pycache__/authentication.cpython-36.pyc
rest_social_email_auth/__pycache__/backends.cpython-36.pyc
rest_social_email_auth/__pycache__/factories.cpython-36.pyc
rest_social_email_auth/__pycache__/generics.cpython-36.pyc
rest_social_email_auth/__pycache__/managers.cpython-36.pyc
rest_social_email_auth/__pycache__/models.cpython-36.pyc
rest_social_email_auth/__pycache__/serializers.cpython-36.pyc
rest_social_email_auth/__pycache__/signals.cpython-36.pyc
rest_social_email_auth/__pycache__/urls.cpython-36.pyc
rest_social_email_auth/__pycache__/utils.cpython-36.pyc
rest_social_email_auth/__pycache__/views.cpython-36.pyc
rest_social_email_auth/management/__init__.py
rest_social_email_auth/management/__pycache__/__init__.cpython-36.pyc
rest_social_email_auth/management/commands/__init__.py
rest_social_email_auth/management/commands/cleanemailconfirmations.py
rest_social_email_auth/management/commands/__pycache__/__init__.cpython-36.pyc
rest_social_email_auth/management/commands/__pycache__/cleanemailconfirmations.cpython-36.pyc
rest_social_email_auth/migrations/0001_initial.py
rest_social_email_auth/migrations/0002_emailaddress.py
rest_social_email_auth/migrations/0003_emailconfirmation.py
rest_social_email_auth/migrations/0004_passwordresettoken.py
rest_social_email_auth/migrations/__init__.py
django_rest_social_email_allauth-0.1.0.dist-info/LICENSE
django_rest_social_email_allauth-0.1.0.dist-info/METADATA
django_rest_social_email_allauth-0.1.0.dist-info/WHEEL
django_rest_social_email_allauth-0.1.0.dist-info/top_level.txt
django_rest_social_email_allauth-0.1.0.dist-info/RECORD
