Metadata-Version: 2.1
Name: django-rest-social-email-allauth
Version: 0.1.0
Summary: This is an authentication module template with social (Oauth2) Authentication, knox-rest and email account verification with password reset framework.
Home-page: https://github.com/hacknd/django-rest-social-email-auth
Author: HackND
Author-email: benkaranja43@gmail.com
License: MIT
Platform: UNKNOWN
Classifier: Development Status :: 3 - Alpha
Classifier: Framework :: Django
Classifier: Intended Audience :: Developers
Classifier: Natural Language :: English
Classifier: Programming Language :: Python
Requires-Dist: Django (>=3.0)
Requires-Dist: djangorestframework (>=3.0)
Requires-Dist: django-email-utils (<1.0)
Requires-Dist: django-rest-knox (>4.0)
Requires-Dist: social-auth-app-django (<=3.1.0)
Requires-Dist: rest-social-auth (>=2.1.0)
